{"CMCSA_MAR": {"beta_win": 1936, "z_win": 152, "z_entry": 3.0, "z_exit": 0.8, "z_stop_scaler": 1.5, "trade_freq": "3m", "stop_loss": 0.025}, "GOOGL_MU": {"beta_win": 1104, "z_win": 488, "z_entry": 1.4, "z_exit": 0.8, "z_stop_scaler": 0.5, "trade_freq": "2m", "stop_loss": 0.045000000000000005}, "GOOG_MU": {"beta_win": 3592, "z_win": 312, "z_entry": 1.6, "z_exit": 0.8, "z_stop_scaler": 1.5, "trade_freq": "7m", "stop_loss": 0.05}, "CPRT_MSFT": {"beta_win": 7000, "z_win": 376, "z_entry": 2.6, "z_exit": 0.0, "z_stop_scaler": 1.5, "trade_freq": "8m", "stop_loss": 0.04}, "GOOGL_VRSK": {"beta_win": 5440, "z_win": 800, "z_entry": 1.4, "z_exit": 0.6000000000000001, "z_stop_scaler": 1.5, "trade_freq": "8m", "stop_loss": 0.05}, "GOOG_VRSK": {"beta_win": 6224, "z_win": 680, "z_entry": 2.6, "z_exit": 0.4, "z_stop_scaler": 0.5, "trade_freq": "3m", "stop_loss": 0.02}, "AMZN_LRCX": {"beta_win": 5496, "z_win": 456, "z_entry": 2.0, "z_exit": 0.6000000000000001, "z_stop_scaler": 1.0, "trade_freq": "2m", "stop_loss": 0.035}, "CTAS_INTC": {"beta_win": 1104, "z_win": 1008, "z_entry": 2.0, "z_exit": 0.2, "z_stop_scaler": 2.0, "trade_freq": "2m", "stop_loss": 0.05}, "CPRT_MU": {"beta_win": 7880, "z_win": 1000, "z_entry": 2.0, "z_exit": 0.4, "z_stop_scaler": 2.0, "trade_freq": "4m", "stop_loss": 0.05}, "CSGP_CSX": {"beta_win": 5720, "z_win": 160, "z_entry": 2.2, "z_exit": 1.0, "z_stop_scaler": 2.0, "trade_freq": "3m", "stop_loss": 0.025}, "FTNT_ROST": {"beta_win": 2216, "z_win": 312, "z_entry": 1.2, "z_exit": 0.4, "z_stop_scaler": 0.5, "trade_freq": "9m", "stop_loss": 0.02}, "pairs_to_trade": 10, "buffer_capital": 0.1}